{
  "info": {
    "_postman_id": "9f78c9c0-7e2c-4b17-b5c9-2e638c80f001",
    "name": "Ferreteria BFF API",
    "description": "Postman Collection v2.1 generated from the current BFF controllers and DTOs. Base URL: http://localhost:8080.",
    "schema": "https://schema.getpostman.com/json/collection/v2.1.0/collection.json"
  },
  "variable": [
    {
      "key": "baseUrl",
      "value": "http://localhost:8080",
      "type": "string"
    },
    {
      "key": "jwtToken",
      "value": "",
      "type": "string"
    },
    {
      "key": "productId",
      "value": "",
      "type": "string"
    },
    {
      "key": "saleId",
      "value": "",
      "type": "string"
    },
    {
      "key": "notificationId",
      "value": "",
      "type": "string"
    },
    {
      "key": "username",
      "value": "qa_user_{{$timestamp}}",
      "type": "string"
    },
    {
      "key": "password",
      "value": "Pass1234",
      "type": "string"
    }
  ],
  "item": [
    {
      "name": "Auth",
      "item": [
        {
          "name": "Register User",
          "event": [
            {
              "listen": "test",
              "script": {
                "type": "text/javascript",
                "exec": [
                  "pm.test(\"Status is 201\", function () {",
                  "  pm.response.to.have.status(201);",
                  "});",
                  "",
                  "const requestBody = JSON.parse(pm.request.body.raw);",
                  "pm.collectionVariables.set(\"username\", requestBody.username);",
                  "pm.collectionVariables.set(\"password\", requestBody.password);"
                ]
              }
            }
          ],
          "request": {
            "method": "POST",
            "header": [
              {
                "key": "Content-Type",
                "value": "application/json"
              }
            ],
            "body": {
              "mode": "raw",
              "raw": "{\n  \"username\": \"qa_user_{{$timestamp}}\",\n  \"password\": \"{{password}}\"\n}"
            },
            "url": {
              "raw": "{{baseUrl}}/api/auth/register",
              "host": [
                "{{baseUrl}}"
              ],
              "path": [
                "api",
                "auth",
                "register"
              ]
            },
            "description": "Request DTO: RegisterRequestDto. Response DTO: MessageResponseDto."
          },
          "response": []
        },
        {
          "name": "Login",
          "event": [
            {
              "listen": "test",
              "script": {
                "type": "text/javascript",
                "exec": [
                  "pm.test(\"Status is 200\", function () {",
                  "  pm.response.to.have.status(200);",
                  "});",
                  "",
                  "const response = pm.response.json();",
                  "pm.collectionVariables.set(\"jwtToken\", response.token);"
                ]
              }
            }
          ],
          "request": {
            "method": "POST",
            "header": [
              {
                "key": "Content-Type",
                "value": "application/json"
              }
            ],
            "body": {
              "mode": "raw",
              "raw": "{\n  \"username\": \"{{username}}\",\n  \"password\": \"{{password}}\"\n}"
            },
            "url": {
              "raw": "{{baseUrl}}/api/auth/login",
              "host": [
                "{{baseUrl}}"
              ],
              "path": [
                "api",
                "auth",
                "login"
              ]
            },
            "description": "Request DTO: LoginRequestDto. Response DTO: AuthResponseDto."
          },
          "response": []
        }
      ]
    },
    {
      "name": "Health",
      "item": [
        {
          "name": "Health",
          "request": {
            "method": "GET",
            "header": [],
            "url": {
              "raw": "{{baseUrl}}/health",
              "host": [
                "{{baseUrl}}"
              ],
              "path": [
                "health"
              ]
            },
            "description": "Response DTO: HealthResponseDto."
          },
          "response": []
        }
      ]
    },
    {
      "name": "Products",
      "item": [
        {
          "name": "Create Product",
          "event": [
            {
              "listen": "test",
              "script": {
                "type": "text/javascript",
                "exec": [
                  "pm.test(\"Status is 201\", function () {",
                  "  pm.response.to.have.status(201);",
                  "});",
                  "",
                  "const response = pm.response.json();",
                  "pm.collectionVariables.set(\"productId\", response.id);"
                ]
              }
            }
          ],
          "request": {
            "auth": {
              "type": "bearer",
              "bearer": [
                {
                  "key": "token",
                  "value": "{{jwtToken}}",
                  "type": "string"
                }
              ]
            },
            "method": "POST",
            "header": [
              {
                "key": "Content-Type",
                "value": "application/json"
              }
            ],
            "body": {
              "mode": "raw",
              "raw": "{\n  \"nombre\": \"Taladro {{$timestamp}}\",\n  \"descripcion\": \"Taladro profesional\",\n  \"precio\": 89990,\n  \"categoria\": \"Herramientas\"\n}"
            },
            "url": {
              "raw": "{{baseUrl}}/api/products",
              "host": [
                "{{baseUrl}}"
              ],
              "path": [
                "api",
                "products"
              ]
            },
            "description": "Request DTO: ProductRequestDto. Response DTO: ProductResponseDto."
          },
          "response": []
        },
        {
          "name": "List Products",
          "request": {
            "auth": {
              "type": "bearer",
              "bearer": [
                {
                  "key": "token",
                  "value": "{{jwtToken}}",
                  "type": "string"
                }
              ]
            },
            "method": "GET",
            "header": [],
            "url": {
              "raw": "{{baseUrl}}/api/products",
              "host": [
                "{{baseUrl}}"
              ],
              "path": [
                "api",
                "products"
              ]
            },
            "description": "Response DTO: List<ProductResponseDto>."
          },
          "response": []
        },
        {
          "name": "Get Product",
          "request": {
            "auth": {
              "type": "bearer",
              "bearer": [
                {
                  "key": "token",
                  "value": "{{jwtToken}}",
                  "type": "string"
                }
              ]
            },
            "method": "GET",
            "header": [],
            "url": {
              "raw": "{{baseUrl}}/api/products/{{productId}}",
              "host": [
                "{{baseUrl}}"
              ],
              "path": [
                "api",
                "products",
                "{{productId}}"
              ]
            },
            "description": "Response DTO: ProductResponseDto."
          },
          "response": []
        },
        {
          "name": "Search Products By Name",
          "request": {
            "auth": {
              "type": "bearer",
              "bearer": [
                {
                  "key": "token",
                  "value": "{{jwtToken}}",
                  "type": "string"
                }
              ]
            },
            "method": "GET",
            "header": [],
            "url": {
              "raw": "{{baseUrl}}/api/products/buscar?nombre=Taladro",
              "host": [
                "{{baseUrl}}"
              ],
              "path": [
                "api",
                "products",
                "buscar"
              ],
              "query": [
                {
                  "key": "nombre",
                  "value": "Taladro"
                }
              ]
            },
            "description": "Response DTO: List<ProductResponseDto>."
          },
          "response": []
        },
        {
          "name": "Search Products By Category",
          "request": {
            "auth": {
              "type": "bearer",
              "bearer": [
                {
                  "key": "token",
                  "value": "{{jwtToken}}",
                  "type": "string"
                }
              ]
            },
            "method": "GET",
            "header": [],
            "url": {
              "raw": "{{baseUrl}}/api/products/categoria/Herramientas",
              "host": [
                "{{baseUrl}}"
              ],
              "path": [
                "api",
                "products",
                "categoria",
                "Herramientas"
              ]
            },
            "description": "Response DTO: List<ProductResponseDto>."
          },
          "response": []
        },
        {
          "name": "Update Product",
          "request": {
            "auth": {
              "type": "bearer",
              "bearer": [
                {
                  "key": "token",
                  "value": "{{jwtToken}}",
                  "type": "string"
                }
              ]
            },
            "method": "PUT",
            "header": [
              {
                "key": "Content-Type",
                "value": "application/json"
              }
            ],
            "body": {
              "mode": "raw",
              "raw": "{\n  \"nombre\": \"Taladro Pro {{$timestamp}}\",\n  \"descripcion\": \"Taladro profesional actualizado\",\n  \"precio\": 99990,\n  \"categoria\": \"Herramientas\"\n}"
            },
            "url": {
              "raw": "{{baseUrl}}/api/products/{{productId}}",
              "host": [
                "{{baseUrl}}"
              ],
              "path": [
                "api",
                "products",
                "{{productId}}"
              ]
            },
            "description": "Request DTO: ProductRequestDto. Response DTO: ProductResponseDto."
          },
          "response": []
        },
        {
          "name": "Deactivate Product",
          "request": {
            "auth": {
              "type": "bearer",
              "bearer": [
                {
                  "key": "token",
                  "value": "{{jwtToken}}",
                  "type": "string"
                }
              ]
            },
            "method": "DELETE",
            "header": [],
            "url": {
              "raw": "{{baseUrl}}/api/products/{{productId}}",
              "host": [
                "{{baseUrl}}"
              ],
              "path": [
                "api",
                "products",
                "{{productId}}"
              ]
            },
            "description": "Response DTO: MessageResponseDto."
          },
          "response": []
        }
      ]
    },
    {
      "name": "Inventory",
      "item": [
        {
          "name": "Create Inventory",
          "request": {
            "auth": {
              "type": "bearer",
              "bearer": [
                {
                  "key": "token",
                  "value": "{{jwtToken}}",
                  "type": "string"
                }
              ]
            },
            "method": "POST",
            "header": [
              {
                "key": "Content-Type",
                "value": "application/json"
              }
            ],
            "body": {
              "mode": "raw",
              "raw": "{\n  \"productId\": \"{{productId}}\",\n  \"stock\": 10,\n  \"stockMinimo\": 5,\n  \"bodega\": \"Principal\"\n}"
            },
            "url": {
              "raw": "{{baseUrl}}/api/inventory",
              "host": [
                "{{baseUrl}}"
              ],
              "path": [
                "api",
                "inventory"
              ]
            },
            "description": "Request DTO: InventoryRequestDto. Response DTO: InventoryResponseDto."
          },
          "response": []
        },
        {
          "name": "List Inventory",
          "request": {
            "auth": {
              "type": "bearer",
              "bearer": [
                {
                  "key": "token",
                  "value": "{{jwtToken}}",
                  "type": "string"
                }
              ]
            },
            "method": "GET",
            "header": [],
            "url": {
              "raw": "{{baseUrl}}/api/inventory",
              "host": [
                "{{baseUrl}}"
              ],
              "path": [
                "api",
                "inventory"
              ]
            },
            "description": "Response DTO: List<InventoryResponseDto>."
          },
          "response": []
        },
        {
          "name": "List Low Stock",
          "request": {
            "auth": {
              "type": "bearer",
              "bearer": [
                {
                  "key": "token",
                  "value": "{{jwtToken}}",
                  "type": "string"
                }
              ]
            },
            "method": "GET",
            "header": [],
            "url": {
              "raw": "{{baseUrl}}/api/inventory/stock-bajo",
              "host": [
                "{{baseUrl}}"
              ],
              "path": [
                "api",
                "inventory",
                "stock-bajo"
              ]
            },
            "description": "Response DTO: List<InventoryResponseDto>."
          },
          "response": []
        },
        {
          "name": "Get Inventory By Product",
          "request": {
            "auth": {
              "type": "bearer",
              "bearer": [
                {
                  "key": "token",
                  "value": "{{jwtToken}}",
                  "type": "string"
                }
              ]
            },
            "method": "GET",
            "header": [],
            "url": {
              "raw": "{{baseUrl}}/api/inventory/producto/{{productId}}",
              "host": [
                "{{baseUrl}}"
              ],
              "path": [
                "api",
                "inventory",
                "producto",
                "{{productId}}"
              ]
            },
            "description": "Response DTO: InventoryResponseDto."
          },
          "response": []
        },
        {
          "name": "Add Stock",
          "request": {
            "auth": {
              "type": "bearer",
              "bearer": [
                {
                  "key": "token",
                  "value": "{{jwtToken}}",
                  "type": "string"
                }
              ]
            },
            "method": "PUT",
            "header": [
              {
                "key": "Content-Type",
                "value": "application/json"
              }
            ],
            "body": {
              "mode": "raw",
              "raw": "{\n  \"cantidad\": 5\n}"
            },
            "url": {
              "raw": "{{baseUrl}}/api/inventory/producto/{{productId}}/agregar",
              "host": [
                "{{baseUrl}}"
              ],
              "path": [
                "api",
                "inventory",
                "producto",
                "{{productId}}",
                "agregar"
              ]
            },
            "description": "Request DTO: StockAdjustmentDto. Response DTO: InventoryResponseDto."
          },
          "response": []
        },
        {
          "name": "Subtract Stock",
          "request": {
            "auth": {
              "type": "bearer",
              "bearer": [
                {
                  "key": "token",
                  "value": "{{jwtToken}}",
                  "type": "string"
                }
              ]
            },
            "method": "PUT",
            "header": [
              {
                "key": "Content-Type",
                "value": "application/json"
              }
            ],
            "body": {
              "mode": "raw",
              "raw": "{\n  \"cantidad\": 2\n}"
            },
            "url": {
              "raw": "{{baseUrl}}/api/inventory/producto/{{productId}}/descontar",
              "host": [
                "{{baseUrl}}"
              ],
              "path": [
                "api",
                "inventory",
                "producto",
                "{{productId}}",
                "descontar"
              ]
            },
            "description": "Request DTO: StockAdjustmentDto. Response DTO: InventoryResponseDto."
          },
          "response": []
        }
      ]
    },
    {
      "name": "Sales",
      "item": [
        {
          "name": "Register Sale",
          "event": [
            {
              "listen": "test",
              "script": {
                "type": "text/javascript",
                "exec": [
                  "pm.test(\"Status is 201\", function () {",
                  "  pm.response.to.have.status(201);",
                  "});",
                  "",
                  "const response = pm.response.json();",
                  "pm.collectionVariables.set(\"saleId\", response.id);"
                ]
              }
            }
          ],
          "request": {
            "auth": {
              "type": "bearer",
              "bearer": [
                {
                  "key": "token",
                  "value": "{{jwtToken}}",
                  "type": "string"
                }
              ]
            },
            "method": "POST",
            "header": [
              {
                "key": "Content-Type",
                "value": "application/json"
              }
            ],
            "body": {
              "mode": "raw",
              "raw": "{\n  \"productId\": \"{{productId}}\",\n  \"cantidad\": 2,\n  \"cliente\": \"Cliente QA\"\n}"
            },
            "url": {
              "raw": "{{baseUrl}}/api/sales",
              "host": [
                "{{baseUrl}}"
              ],
              "path": [
                "api",
                "sales"
              ]
            },
            "description": "Request DTO: SaleRequestDto. Response DTO: SaleResponseDto."
          },
          "response": []
        },
        {
          "name": "List Sales",
          "request": {
            "auth": {
              "type": "bearer",
              "bearer": [
                {
                  "key": "token",
                  "value": "{{jwtToken}}",
                  "type": "string"
                }
              ]
            },
            "method": "GET",
            "header": [],
            "url": {
              "raw": "{{baseUrl}}/api/sales",
              "host": [
                "{{baseUrl}}"
              ],
              "path": [
                "api",
                "sales"
              ]
            },
            "description": "Response DTO: List<SaleResponseDto>."
          },
          "response": []
        },
        {
          "name": "Get Sale",
          "request": {
            "auth": {
              "type": "bearer",
              "bearer": [
                {
                  "key": "token",
                  "value": "{{jwtToken}}",
                  "type": "string"
                }
              ]
            },
            "method": "GET",
            "header": [],
            "url": {
              "raw": "{{baseUrl}}/api/sales/{{saleId}}",
              "host": [
                "{{baseUrl}}"
              ],
              "path": [
                "api",
                "sales",
                "{{saleId}}"
              ]
            },
            "description": "Response DTO: SaleResponseDto."
          },
          "response": []
        },
        {
          "name": "List Sales By Product",
          "request": {
            "auth": {
              "type": "bearer",
              "bearer": [
                {
                  "key": "token",
                  "value": "{{jwtToken}}",
                  "type": "string"
                }
              ]
            },
            "method": "GET",
            "header": [],
            "url": {
              "raw": "{{baseUrl}}/api/sales/producto/{{productId}}",
              "host": [
                "{{baseUrl}}"
              ],
              "path": [
                "api",
                "sales",
                "producto",
                "{{productId}}"
              ]
            },
            "description": "Response DTO: List<SaleResponseDto>."
          },
          "response": []
        },
        {
          "name": "Sales Summary",
          "request": {
            "auth": {
              "type": "bearer",
              "bearer": [
                {
                  "key": "token",
                  "value": "{{jwtToken}}",
                  "type": "string"
                }
              ]
            },
            "method": "GET",
            "header": [],
            "url": {
              "raw": "{{baseUrl}}/api/sales/resumen",
              "host": [
                "{{baseUrl}}"
              ],
              "path": [
                "api",
                "sales",
                "resumen"
              ]
            },
            "description": "Response DTO: SalesSummaryDto."
          },
          "response": []
        }
      ]
    },
    {
      "name": "Notifications",
      "item": [
        {
          "name": "List Notifications",
          "event": [
            {
              "listen": "test",
              "script": {
                "type": "text/javascript",
                "exec": [
                  "pm.test(\"Status is 200\", function () {",
                  "  pm.response.to.have.status(200);",
                  "});",
                  "",
                  "const response = pm.response.json();",
                  "if (Array.isArray(response) && response.length > 0) {",
                  "  pm.collectionVariables.set(\"notificationId\", response[0].id);",
                  "}"
                ]
              }
            }
          ],
          "request": {
            "auth": {
              "type": "bearer",
              "bearer": [
                {
                  "key": "token",
                  "value": "{{jwtToken}}",
                  "type": "string"
                }
              ]
            },
            "method": "GET",
            "header": [],
            "url": {
              "raw": "{{baseUrl}}/api/notifications",
              "host": [
                "{{baseUrl}}"
              ],
              "path": [
                "api",
                "notifications"
              ]
            },
            "description": "Response DTO: List<NotificationResponseDto>."
          },
          "response": []
        },
        {
          "name": "List Unread Notifications",
          "event": [
            {
              "listen": "test",
              "script": {
                "type": "text/javascript",
                "exec": [
                  "const response = pm.response.json();",
                  "if (Array.isArray(response) && response.length > 0) {",
                  "  pm.collectionVariables.set(\"notificationId\", response[0].id);",
                  "}"
                ]
              }
            }
          ],
          "request": {
            "auth": {
              "type": "bearer",
              "bearer": [
                {
                  "key": "token",
                  "value": "{{jwtToken}}",
                  "type": "string"
                }
              ]
            },
            "method": "GET",
            "header": [],
            "url": {
              "raw": "{{baseUrl}}/api/notifications/no-leidas",
              "host": [
                "{{baseUrl}}"
              ],
              "path": [
                "api",
                "notifications",
                "no-leidas"
              ]
            },
            "description": "Response DTO: List<NotificationResponseDto>."
          },
          "response": []
        },
        {
          "name": "Mark Notification As Read",
          "request": {
            "auth": {
              "type": "bearer",
              "bearer": [
                {
                  "key": "token",
                  "value": "{{jwtToken}}",
                  "type": "string"
                }
              ]
            },
            "method": "PUT",
            "header": [],
            "url": {
              "raw": "{{baseUrl}}/api/notifications/{{notificationId}}/leer",
              "host": [
                "{{baseUrl}}"
              ],
              "path": [
                "api",
                "notifications",
                "{{notificationId}}",
                "leer"
              ]
            },
            "description": "Response DTO: NotificationResponseDto."
          },
          "response": []
        },
        {
          "name": "Mark All Notifications As Read",
          "request": {
            "auth": {
              "type": "bearer",
              "bearer": [
                {
                  "key": "token",
                  "value": "{{jwtToken}}",
                  "type": "string"
                }
              ]
            },
            "method": "PUT",
            "header": [],
            "url": {
              "raw": "{{baseUrl}}/api/notifications/leer-todas",
              "host": [
                "{{baseUrl}}"
              ],
              "path": [
                "api",
                "notifications",
                "leer-todas"
              ]
            },
            "description": "Response DTO: MessageResponseDto."
          },
          "response": []
        }
      ]
    }
  ]
}
